NeuralNetworkMLP/Activations.py
NeuralNetworkMLP/Layer.py
NeuralNetworkMLP/LoadDataset.py
NeuralNetworkMLP/NeuralNetwork.py
NeuralNetworkMLP/Plot.py
NeuralNetworkMLP/__init__.py
neuralnetworkmlp-1.1.2.dist-info/licenses/LICENCE
neuralnetworkmlp-1.1.2.dist-info/METADATA
neuralnetworkmlp-1.1.2.dist-info/WHEEL
neuralnetworkmlp-1.1.2.dist-info/top_level.txt
neuralnetworkmlp-1.1.2.dist-info/RECORD
