Metadata-Version: 2.4
Name: NeuralNetworkMLP
Version: 1.1.2
Summary: A class that implements an MLP neural network
Home-page: https://github.com/ThePhantom2307/MLP-Neural-Network
Author: Panagiotis Trypos
Author-email: panagiotis.trypos23@gmail.com
Classifier: Programming Language :: Python :: 3
Classifier: License :: OSI Approved :: MIT License
Classifier: Operating System :: OS Independent
Requires-Python: >=3.6
License-File: LICENCE
Dynamic: author
Dynamic: author-email
Dynamic: classifier
Dynamic: description
Dynamic: description-content-type
Dynamic: home-page
Dynamic: license-file
Dynamic: requires-python
Dynamic: summary
